{
  "name": "Test Level 2",
  "description": "A very simple test with 3 employees and a duty that requires 2 employees",
  "start_date": "2025-05-01",
  "end_date": "2025-05-07",
  "employees": [
    {
      "id": 0,
      "name": "Anna Schmidt",
      "max_days_in_a_row": 6,
      "off_days": [
        "2025-05-03"
      ],
      "max_hours_per_day": 8,
      "max_hours_in_period": 40,
      "work_percentage": 100
    },
    {
      "id": 1,
      "name": "Ben Weber",
      "max_days_in_a_row": 6,
      "off_days": [
        "2025-05-06"
      ],
      "max_hours_per_day": 8,
      "max_hours_in_period": 40,
      "work_percentage": 100
    },
    {
      "id": 2,
      "name": "Garry Smith",
      "max_days_in_a_row": 6,
      "off_days": [
        "2025-05-02"
      ],
      "max_hours_per_day": 8,
      "max_hours_in_period": 40,
      "work_percentage": 100
    }
  ],
  "duties": [
    {
      "code": "DIS",
      "required_employees": 2,
      "start_time": "04:00",
      "end_time": "13:00",
      "date": "2025-05-01",
      "id": 0,
      "working_minutes": 540
    },
    {
      "code": "DIS",
      "required_employees": 2,
      "start_time": "04:00",
      "end_time": "13:00",
      "date": "2025-05-02",
      "id": 1,
      "working_minutes": 540
    },
    {
      "code": "DIS",
      "required_employees": 2,
      "start_time": "04:00",
      "end_time": "13:00",
      "date": "2025-05-03",
      "id": 2,
      "working_minutes": 540
    },
    {
      "code": "DIS",
      "required_employees": 2,
      "start_time": "04:00",
      "end_time": "13:00",
      "date": "2025-05-04",
      "id": 3,
      "working_minutes": 540
    },
    {
      "code": "DIS",
      "required_employees": 2,
      "start_time": "04:00",
      "end_time": "13:00",
      "date": "2025-05-05",
      "id": 4,
      "working_minutes": 540
    },
    {
      "code": "DIS",
      "required_employees": 2,
      "start_time": "04:00",
      "end_time": "13:00",
      "date": "2025-05-06",
      "id": 5,
      "working_minutes": 540
    },
    {
      "code": "DIS",
      "required_employees": 2,
      "start_time": "04:00",
      "end_time": "13:00",
      "date": "2025-05-07",
      "id": 6,
      "working_minutes": 540
    }
  ]
}